{
  "collection": "items_items",
  "field": "related_items_id",
  "related_collection": "items",
  "meta": {
    "junction_field": "items_id",
    "many_collection": "items_items",
    "many_field": "related_items_id",
    "one_allowed_collections": null,
    "one_collection": "items",
    "one_collection_field": null,
    "one_deselect_action": "nullify",
    "one_field": null,
    "sort_field": null
  },
  "schema": {
    "table": "items_items",
    "column": "related_items_id",
    "foreign_key_table": "items",
    "foreign_key_column": "id",
    "constraint_name": "items_items_related_items_id_foreign",
    "on_update": "NO ACTION",
    "on_delete": "SET NULL"
  }
}
